covid19/__init__.py
covid19/scrape.py
covid_19_us_data-0.0.3.dist-info/LICENSE
covid_19_us_data-0.0.3.dist-info/METADATA
covid_19_us_data-0.0.3.dist-info/WHEEL
covid_19_us_data-0.0.3.dist-info/top_level.txt
covid_19_us_data-0.0.3.dist-info/RECORD
