Metadata-Version: 2.1
Name: covid-19-us-data
Version: 0.0.3
Summary: A COVID-19 web scrapping tool used to scrap data from the Worldometer website of US cases
Home-page: UNKNOWN
Author: Jimmy Tran
Author-email: jimmytran1620@gmail.com
License: UNKNOWN
Keywords: covid19,covid,web scraping,beautifulsoup
Platform: UNKNOWN
Classifier: Development Status :: 1 - Planning
Classifier: Intended Audience :: Developers
Classifier: Programming Language :: Python :: 3
Classifier: Operating System :: Unix
Classifier: Operating System :: MacOS :: MacOS X
Classifier: Operating System :: Microsoft :: Windows
Requires-Dist: beautifulsoup4 (==4.9.1)
Requires-Dist: bs4 (==0.0.1)
Requires-Dist: requests
